setup.py
Flask_Nytro.egg-info/PKG-INFO
Flask_Nytro.egg-info/SOURCES.txt
Flask_Nytro.egg-info/dependency_links.txt
Flask_Nytro.egg-info/requires.txt
Flask_Nytro.egg-info/top_level.txt
flask_nytro/__init__.py
flask_nytro/helpers/__init__.py
flask_nytro/helpers/sqlalchemy.py