Metadata-Version: 1.1
Name: Flask-Nytro
Version: 1.1
Summary: Nytro is an extension to help developer providing a set of useful tools
Home-page: http://github.com/sacanix/Flask-Nytro
Author: Tony Kamillo (Sacanix)
Author-email: tonysacanix@gmail.com
License: BSD
Platform: any
Classifier: Environment :: Web Environment
Classifier: Intended Audience :: Developers
Classifier: License :: OSI Approved :: BSD License
Classifier: Operating System :: OS Independent
Classifier: Programming Language :: Python
Classifier: Topic :: Internet :: WWW/HTTP :: Dynamic Content
Classifier: Topic :: Software Development :: Libraries :: Python Modules
